monticello/__init__.py
monticello/monticello.py
monticello/responses.py
monticello/tests/__init__.py
monticello/tests/fixtures/__init__.py
monticello/tests/test_monticello.py
monticello-0.1.0.dist-info/LICENSE
monticello-0.1.0.dist-info/WHEEL
monticello-0.1.0.dist-info/METADATA
monticello-0.1.0.dist-info/RECORD
